{
    "type":  "minecraft:crafting_shaped",
    "category":  "misc",
    "pattern":  [
                    "PAP",
                    "LRL",
                    "PAP"
                ],
    "key":  {
                "P":  "minecraft:paper",
                "A":  "minecraft:amethyst_shard",
                "L":  "minecraft:lapis_lazuli",
                "R":  "minecraft:redstone"
            },
    "result":  {
                   "id":  "echoconvoyprotocol:cargo_loading_bay_blueprint",
                   "count":  1
               }
}
