{
  "parent": "minecraft:block/block",
  "textures": {
    "particle": "echopowergrid:block/low_voltage_cable_connection",
    "all": "echopowergrid:block/low_voltage_cable_connection"
  },
  "elements": [
    {
      "from": [
        6,
        6,
        0
      ],
      "to": [
        10,
        10,
        6
      ],
      "faces": {
        "down": {
          "texture": "#all",
          "uv": [
            6,
            0,
            10,
            6
          ]
        },
        "up": {
          "texture": "#all",
          "uv": [
            6,
            0,
            10,
            6
          ]
        },
        "north": {
          "texture": "#all",
          "uv": [
            6,
            6,
            10,
            10
          ]
        },
        "south": {
          "texture": "#all",
          "uv": [
            6,
            6,
            10,
            10
          ]
        },
        "west": {
          "texture": "#all",
          "uv": [
            0,
            6,
            6,
            10
          ]
        },
        "east": {
          "texture": "#all",
          "uv": [
            0,
            6,
            6,
            10
          ]
        }
      }
    }
  ]
}
